hello/__init__.py
hello/hello.py
hello50-1.0.0.dist-info/METADATA
hello50-1.0.0.dist-info/WHEEL
hello50-1.0.0.dist-info/top_level.txt
hello50-1.0.0.dist-info/RECORD
